slack_janitor/__init__.py
slack_janitor/main.py
slack_janitor_tool-1.0.dist-info/METADATA
slack_janitor_tool-1.0.dist-info/RECORD
slack_janitor_tool-1.0.dist-info/WHEEL
slack_janitor_tool-1.0.dist-info/entry_points.txt
slack_janitor_tool-1.0.dist-info/top_level.txt
