Metadata-Version: 2.1
Name: slack-janitor-tool
Version: 1.0
Summary: Your stubborn Slack Cleaning tool
Home-page: https://github.com/paraita/slack-janitor
Author: Paraita Wohler
Author-email: paraita.wohler@gmail.com
License: UNKNOWN
Platform: UNKNOWN
Requires-Python: >3.5.0
